civet
