Metadata-Version: 1.1
Name: civet
Version: 2.0.2
Summary: CoffeeScript and Sass asset precompiler for the Django
Home-page: https://github.com/counsyl/civet
Author: Counsyl
Author-email: opensource@counsyl.com
License: Apache License 2.0
Platform: UNKNOWN
Classifier: Development Status :: 5 - Production/Stable
Classifier: Environment :: Web Environment
Classifier: Framework :: Django
Classifier: Intended Audience :: Developers
Classifier: License :: OSI Approved :: Apache Software License
Classifier: Operating System :: OS Independent
Classifier: Programming Language :: Python :: 2
Classifier: Programming Language :: Python :: 3
Classifier: Topic :: Software Development :: Pre-processors
